django_py_reverse/__init__.py
django_py_reverse/urls.py
django_py_reverse-1.0.1.dist-info/LICENSE
django_py_reverse-1.0.1.dist-info/LICENSE.txt
django_py_reverse-1.0.1.dist-info/METADATA
django_py_reverse-1.0.1.dist-info/WHEEL
django_py_reverse-1.0.1.dist-info/RECORD
