Metadata-Version: 2.1
Name: django-py-reverse
Version: 1.0.1
Summary: Python URL handling for Django (based on django-js-reverse)
Home-page: https://github.com/robertpro/django-py-reverse
License: MIT
Keywords: django,url,reverse,js,python,py
Author: Roberto Meza
Author-email: the@robertpro.dev
Maintainer: Roberto Meza
Maintainer-email: the@robertpro.dev
Requires-Python: >=3.9,<4.0
Classifier: Development Status :: 5 - Production/Stable
Classifier: Framework :: Django
Classifier: License :: OSI Approved :: MIT License
Classifier: Programming Language :: Python
Classifier: Programming Language :: Python :: 3
Classifier: Programming Language :: Python :: 3.9
Classifier: Programming Language :: Python :: 3.10
Classifier: Programming Language :: Python :: 3.11
Classifier: Programming Language :: Python :: 3.12
Project-URL: Repository, https://github.com/robertpro/django-py-reverse
